{
  "editorVersion": "6.5.47",
  "docType": "5",
  "title": "blue_clouds",
  "description": "",
  "colors": {},
  "schematics": [
    {
      "docType": "1",
      "title": "schem1",
      "description": "",
      "dataStr": {
        "head": {
          "docType": "1",
          "editorVersion": "6.5.47",
          "newgId": true,
          "c_para": {
            "Prefix Start": "1"
          },
          "c_spiceCmd": "null",
          "hasIdFlag": true,
          "uuid": "26a254744bf841a6bd6680bf88b36bc4",
          "x": "0",
          "y": "0",
          "portOfADImportHack": "",
          "importFlag": 0,
          "transformList": ""
        },
        "canvas": "CA~1000~1000~#FFFFFF~yes~#CCCCCC~15~1000~1000~line~5~pixel~5~0~0",
        "shape": [
          "LIB~0~-790~package`NONE`Manufacturer Part`?`spicePre`.`~~0~frame_lib_1~~~0~e65745c330bd0b41~yes~yes~~~#@$T~N~570.5~-793~0~#880000~Arial~~~~~comment~A~0~start~gge223~0~pinpart#@$PT~M 206 -780 L 206 -790 M 206 6 L 206 16 M 402 -780 L 402 -790 M 402 6 L 402 16 M 598 -780 L 598 -790 M 598 6 L 598 16 M 794 -780 L 794 -790 M 794 6 L 794 16 M 990 -780 L 990 -790 M 990 6 L 990 16 M 10 -584 L 0 -584 M 1139 -584 L 1149 -584 M 10 -388 L 0 -388 M 1139 -388 L 1149 -388 M 10 -192 L 0 -192 M 1139 -192 L 1149 -192 M 10 4 L 0 4 M 1139 4 L 1149 4~#880000~1~0~none~gge10~0~frame_tick#@$T~P~571.5~-802~0~#880000~Arial~~~~~comment~A~0~start~gge220~0~pinpart#@$T~L~1.5~-682~0~#880000~~~~~~comment~A~1~start~gge13~0~frame_tick#@$T~L~1140.5~-682~0~#880000~~~~~~comment~A~1~start~gge19~0~frame_tick#@$T~L~1.5~-486~0~#880000~~~~~~comment~B~1~start~gge25~0~frame_tick#@$T~L~1140.5~-486~0~#880000~~~~~~comment~B~1~start~gge31~0~frame_tick#@$T~L~1.5~-290~0~#880000~~~~~~comment~C~1~start~gge37~0~frame_tick#@$T~L~1140.5~-290~0~#880000~~~~~~comment~C~1~start~gge43~0~frame_tick#@$T~L~1.5~-94~0~#880000~~~~~~comment~D~1~start~gge49~0~frame_tick#@$T~L~1140.5~-94~0~#880000~~~~~~comment~D~1~start~gge55~0~frame_tick#@$T~L~108~-781.5~0~#880000~~~~~~comment~1~1~start~gge61~0~frame_tick#@$T~L~108~14.5~0~#880000~~~~~~comment~1~1~start~gge67~0~frame_tick#@$T~L~304~-781.5~0~#880000~~~~~~comment~2~1~start~gge73~0~frame_tick#@$T~L~304~14.5~0~#880000~~~~~~comment~2~1~start~gge79~0~frame_tick#@$T~L~500~-781.5~0~#880000~~~~~~comment~3~1~start~gge85~0~frame_tick#@$T~L~500~14.5~0~#880000~~~~~~comment~3~1~start~gge91~0~frame_tick#@$T~L~696~-781.5~0~#880000~~~~~~comment~4~1~start~gge97~0~frame_tick#@$T~L~696~14.5~0~#880000~~~~~~comment~4~1~start~gge103~0~frame_tick#@$T~L~892~-781.5~0~#880000~~~~~~comment~5~1~start~gge109~0~frame_tick#@$T~L~892~14.5~0~#880000~~~~~~comment~5~1~start~gge115~0~frame_tick#@$R~10~-780~~~1129~786~#880000~1~0~none~gge121~0~frame_innerbox#@$R~0~-790~~~1149~806~#880000~1~0~none~gge124~0~frame_outbox#@$R~694.99995~-74~~~444~80~#880000~1~0~none~gge127~0~frame_hitarea#@$PL~695.1 -34.75 1138.63 -34.75~#880000~1~0~none~gge130~0#@$PL~799.63 -14.75 1138.63 -14.75~#880000~1~0~none~gge133~0#@$PL~1059.61 -73.93 1059.63 -34.75~#880000~1~0~none~gge136~0#@$PL~1059.63 -34.75 1059.63 -14.75~#880000~1~0~none~gge139~0#@$T~L~699.99995~-61~0~#880000~~8pt~~~~comment~TITLE:~1~start~gge142~0~pinpart#@$T~L~757.62495~-48.41~0~#880000~~10pt~~~~comment~pcb_busniness card~1~start~gge148~0~frame_title#@$T~L~1064.62495~-47.75~0~#880000~~8pt~~~~comment~REV:~1~start~gge154~0~pinpart#@$T~L~1102.62495~-47.75~0~#880000~~9pt~~~~comment~1.0~1~start~gge160~0~frame_version#@$T~L~804.62495~1~0~#880000~~8pt~~~~comment~Date:~1~start~gge166~0~pinpart#@$T~L~851.62495~1.48~0~#880000~~9pt~~~~comment~2024-07-21~1~start~gge172~0~frame_date#@$T~L~1063.62495~-19~0~#880000~~8pt~~~~comment~Sheet:~1~start~gge178~0~pinpart#@$T~L~1108.62495~-18.52~0~#880000~~9pt~~~~comment~1/1~1~start~gge184~0~frame_sheet#@$T~L~943.62495~1.25~0~#880000~~8pt~~~~comment~Drawn By:~1~start~gge190~0~pinpart#@$T~L~1008.63~1.25~0~#880000~~9pt~~~~comment~ministermonkeya1~1~start~gge196~0~frame_drawn#@$T~L~804.62495~-20.75~0~#880000~~8pt~~~~comment~Company:~1~start~gge202~0~pinpart#@$T~L~871.24995~-20.64~0~#880000~~9pt~~~~comment~Your Company~1~start~gge208~0~frame_company#@$PL~799.63 -34.75 799.63 5.25~#880000~1~0~none~gge214~0",
          "LIB~880~-265~package`WIFIM-SMD_ESP-12F-ESP8266MOD`nameAlias`Value`Supplier`LCSC`Manufacturer`Ai-Thinker(安信可)`Manufacturer Part`ESP-12F(ESP8266MOD)`Supplier Part`C82891`JLCPCB Part Class`Extended Part`spicePre`U`spiceSymbolName`ESP-12F(ESP8266MOD)`~~0~ggea8a1398c5e84265b~21bb26c585544e17a64bb2b57131b3de~b5953d65a4054165b11dfc39ebcbd953~0~5b7ef8607db7dfd7~yes~yes~f0aeb487e7304cb590d671f523ea1ac7~1721377201~e0db13e0cd754bd28d9c0113ff859a79#@$T~N~874.06~-328~0~#000080~Arial~~~~~comment~2.4GHz~1~start~gge232~0~pinpart#@$T~P~874.06~-337~0~#000080~Arial~~~~~comment~U1~1~start~gge238~0~pinpart#@$R~835~-325~2~2~90~120~#880000~1~0~none~gge244~0~#@$E~840~-320~1.5~1.5~#880000~1~0~#880000~gge247~0#@$P~show~0~1~825~-315~180~gge250~0^^825~-315^^M 825 -315 h 10~#880000^^1~838.7~-311~0~RST~start~~~#0000FF^^1~834.5~-316~0~1~end~~~#0000FF^^0~832~-315^^0~M 835 -312 L 838 -315 L 835 -318#@$P~show~0~2~825~-305~180~gge271~0^^825~-305^^M 825 -305 h 10~#880000^^1~838.7~-301~0~ADC~start~~~#0000FF^^1~834.5~-306~0~2~end~~~#0000FF^^0~832~-305^^0~M 835 -302 L 838 -305 L 835 -308#@$P~show~0~3~825~-295~180~gge292~0^^825~-295^^M 825 -295 h 10~#880000^^1~838.7~-291~0~EN~start~~~#0000FF^^1~834.5~-296~0~3~end~~~#0000FF^^0~832~-295^^0~M 835 -292 L 838 -295 L 835 -298#@$P~show~0~4~825~-285~180~gge313~0^^825~-285^^M 825 -285 h 10~#880000^^1~838.7~-281~0~GPIO16~start~~~#0000FF^^1~834.5~-286~0~4~end~~~#0000FF^^0~832~-285^^0~M 835 -282 L 838 -285 L 835 -288#@$P~show~0~5~825~-275~180~gge334~0^^825~-275^^M 825 -275 h 10~#880000^^1~838.7~-271~0~GPIO14~start~~~#0000FF^^1~834.5~-276~0~5~end~~~#0000FF^^0~832~-275^^0~M 835 -272 L 838 -275 L 835 -278#@$P~show~0~6~825~-265~180~gge355~0^^825~-265^^M 825 -265 h 10~#880000^^1~838.7~-261~0~GPIO12~start~~~#0000FF^^1~834.5~-266~0~6~end~~~#0000FF^^0~832~-265^^0~M 835 -262 L 838 -265 L 835 -268#@$P~show~0~7~825~-255~180~gge376~0^^825~-255^^M 825 -255 h 10~#880000^^1~838.7~-251~0~GPIO13~start~~~#0000FF^^1~834.5~-256~0~7~end~~~#0000FF^^0~832~-255^^0~M 835 -252 L 838 -255 L 835 -258#@$P~show~0~8~825~-245~180~gge397~0^^825~-245^^M 825 -245 h 10~#880000^^1~838.7~-241~0~VCC~start~~~#0000FF^^1~834.5~-246~0~8~end~~~#0000FF^^0~832~-245^^0~M 835 -242 L 838 -245 L 835 -248#@$P~show~0~9~825~-235~180~gge430~0^^825~-235^^M 825 -235 h 10~#880000^^1~838.7~-231~0~GND~start~~~#0000FF^^1~834.5~-236~0~9~end~~~#0000FF^^0~832~-235^^0~M 835 -232 L 838 -235 L 835 -238#@$P~show~0~10~825~-225~180~gge451~0^^825~-225^^M 825 -225 h 10~#880000^^1~838.7~-221~0~GPIO15~start~~~#0000FF^^1~834.5~-226~0~10~end~~~#0000FF^^0~832~-225^^0~M 835 -222 L 838 -225 L 835 -228#@$P~show~0~11~825~-215~180~gge472~0^^825~-215^^M 825 -215 h 10~#880000^^1~838.7~-211~0~GPIO2~start~~~#0000FF^^1~834.5~-216~0~11~end~~~#0000FF^^0~832~-215^^0~M 835 -212 L 838 -215 L 835 -218#@$P~show~0~12~935~-215~0~gge493~0^^935~-215^^M 935 -215 h -10~#880000^^1~921.3~-211~0~GPIO0~end~~~#0000FF^^1~925.5~-216~0~12~start~~~#0000FF^^0~928~-215^^0~M 925 -218 L 922 -215 L 925 -212#@$P~show~0~13~935~-225~0~gge514~0^^935~-225^^M 935 -225 h -10~#880000^^1~921.3~-221~0~GPIO4~end~~~#0000FF^^1~925.5~-226~0~13~start~~~#0000FF^^0~928~-225^^0~M 925 -228 L 922 -225 L 925 -222#@$P~show~0~14~935~-235~0~gge535~0^^935~-235^^M 935 -235 h -10~#880000^^1~921.3~-231~0~GPIO5~end~~~#0000FF^^1~925.5~-236~0~14~start~~~#0000FF^^0~928~-235^^0~M 925 -238 L 922 -235 L 925 -232#@$P~show~0~15~935~-245~0~gge556~0^^935~-245^^M 935 -245 h -10~#880000^^1~921.3~-241~0~RXD0~end~~~#0000FF^^1~925.5~-246~0~15~start~~~#0000FF^^0~928~-245^^0~M 925 -248 L 922 -245 L 925 -242#@$P~show~0~16~935~-255~0~gge577~0^^935~-255^^M 935 -255 h -10~#880000^^1~921.3~-251~0~TXD0~end~~~#0000FF^^1~925.5~-256~0~16~start~~~#0000FF^^0~928~-255^^0~M 925 -258 L 922 -255 L 925 -252#@$P~show~0~17~935~-265~0~gge598~0^^935~-265^^M 935 -265 h -10~#880000^^1~921.3~-261~0~CS0~end~~~#0000FF^^1~925.5~-266~0~17~start~~~#0000FF^^0~928~-265^^0~M 925 -268 L 922 -265 L 925 -262#@$P~show~0~18~935~-275~0~gge619~0^^935~-275^^M 935 -275 h -10~#880000^^1~921.3~-271~0~MISO~end~~~#0000FF^^1~925.5~-276~0~18~start~~~#0000FF^^0~928~-275^^0~M 925 -278 L 922 -275 L 925 -272#@$P~show~0~19~935~-285~0~gge640~0^^935~-285^^M 935 -285 h -10~#880000^^1~921.3~-281~0~GPIO9~end~~~#0000FF^^1~925.5~-286~0~19~start~~~#0000FF^^0~928~-285^^0~M 925 -288 L 922 -285 L 925 -282#@$P~show~0~20~935~-295~0~gge661~0^^935~-295^^M 935 -295 h -10~#880000^^1~921.3~-291~0~GPIO10~end~~~#0000FF^^1~925.5~-296~0~20~start~~~#0000FF^^0~928~-295^^0~M 925 -298 L 922 -295 L 925 -292#@$P~show~0~21~935~-305~0~gge682~0^^935~-305^^M 935 -305 h -10~#880000^^1~921.3~-301~0~MOSI~end~~~#0000FF^^1~925.5~-306~0~21~start~~~#0000FF^^0~928~-305^^0~M 925 -308 L 922 -305 L 925 -302#@$P~show~0~22~935~-315~0~gge703~0^^935~-315^^M 935 -315 h -10~#880000^^1~921.3~-311~0~SCLK~end~~~#0000FF^^1~925.5~-316~0~22~start~~~#0000FF^^0~928~-315^^0~M 925 -318 L 922 -315 L 925 -312",
          "LIB~560~-195~package`KEY-SMD_2P-L6.2-W3.6-LS8.0`Supplier Part`C118141`Supplier`LCSC`Manufacturer Part`K2-1107ST-A4SW-06`Contributor`LCEDA_Lib`制造商`韩国韩荣`spicePre`K`spiceSymbolName`K2-3.6×6.1_SMD`~~0~gge4238b02df7333b2c~daacbe2eec304950b61eef2efe596556~5c1036b53a4146e4841df4ed0a9de8f0~0~c0e96e395844a962~yes~yes~~1586866326~#@$T~N~548.0703125~-208~0~#000080~Arial~~~~~comment~K2-3.6×6.1_SMD~1~start~gge5494~0~pinpart#@$T~P~548.0703125~-217~0~#000080~Arial~~~~~comment~KEY1~1~start~gge5500~0~pinpart#@$E~570~-195~2~2~#880000~1~0~none~gge5506~0#@$E~550~-195~2~2~#880000~1~0~none~gge5509~0#@$P~show~0~1~535~-195~180~gge5512~0^^535~-195^^M 535 -195 h 13~#880000^^0~550~-192~0~1~start~~~#0000FF^^1~546~-196~0~1~end~~~#0000FF^^0~545~-195^^0~M 548 -192 L 551 -195 L 548 -198#@$P~show~0~2~585~-195~0~gge5533~0^^585~-195^^M 585 -195 h -13~#880000^^0~570~-192~0~2~end~~~#0000FF^^1~575~-196~0~2~start~~~#0000FF^^0~575~-195^^0~M 572 -198 L 569 -195 L 572 -192#@$PL~550 -200 570 -200 570 -201 563 -201 563 -203 557 -203 557 -201 550 -201 550 -200~#880000~1~0~none~gge5554~0",
          "LIB~625~-195~package`KEY-SMD_2P-L6.2-W3.6-LS8.0`Supplier Part`C118141`Supplier`LCSC`Manufacturer Part`K2-1107ST-A4SW-06`Contributor`LCEDA_Lib`制造商`韩国韩荣`spicePre`K`spiceSymbolName`K2-3.6×6.1_SMD`~~0~ggeab2a4f903ec6f949~daacbe2eec304950b61eef2efe596556~5c1036b53a4146e4841df4ed0a9de8f0~0~496fa9eb2c231d87~yes~yes~~1586866326~#@$T~N~614.09~-206.79~0~#000080~Arial~~~~~comment~K2-3.6×6.1_SMD~1~start~gge5563~0~pinpart#@$T~P~613.0703125~-217~0~#000080~Arial~~~~~comment~KEY2~1~start~gge5569~0~pinpart#@$E~635~-195~2~2~#880000~1~0~none~gge5575~0#@$E~615~-195~2~2~#880000~1~0~none~gge5578~0#@$P~show~0~1~600~-195~180~gge5581~0^^600~-195^^M 600 -195 h 13~#880000^^0~615~-192~0~1~start~~~#0000FF^^1~611~-196~0~1~end~~~#0000FF^^0~610~-195^^0~M 613 -192 L 616 -195 L 613 -198#@$P~show~0~2~650~-195~0~gge5602~0^^650~-195^^M 650 -195 h -13~#880000^^0~635~-192~0~2~end~~~#0000FF^^1~640~-196~0~2~start~~~#0000FF^^0~640~-195^^0~M 637 -198 L 634 -195 L 637 -192#@$PL~615 -200 635 -200 635 -201 628 -201 628 -203 622 -203 622 -201 615 -201 615 -200~#880000~1~0~none~gge5623~0",
          "LIB~710~-195~package`KEY-SMD_2P-L6.2-W3.6-LS8.0`Supplier Part`C118141`Supplier`LCSC`Manufacturer Part`K2-1107ST-A4SW-06`Contributor`LCEDA_Lib`制造商`韩国韩荣`spicePre`K`spiceSymbolName`K2-3.6×6.1_SMD`~~0~gge2870213214a84458~daacbe2eec304950b61eef2efe596556~5c1036b53a4146e4841df4ed0a9de8f0~0~c5f015db263901af~yes~yes~~1586866326~#@$T~N~709.08~-207~0~#000080~Arial~~~~~comment~K2-3.6×6.1_SMD~1~start~gge5632~0~pinpart#@$T~P~698.0703125~-217~0~#000080~Arial~~~~~comment~KEY3~1~start~gge5638~0~pinpart#@$E~720~-195~2~2~#880000~1~0~none~gge5644~0#@$E~700~-195~2~2~#880000~1~0~none~gge5647~0#@$P~show~0~1~685~-195~180~gge5650~0^^685~-195^^M 685 -195 h 13~#880000^^0~700~-192~0~1~start~~~#0000FF^^1~696~-196~0~1~end~~~#0000FF^^0~695~-195^^0~M 698 -192 L 701 -195 L 698 -198#@$P~show~0~2~735~-195~0~gge5671~0^^735~-195^^M 735 -195 h -13~#880000^^0~720~-192~0~2~end~~~#0000FF^^1~725~-196~0~2~start~~~#0000FF^^0~725~-195^^0~M 722 -198 L 719 -195 L 722 -192#@$PL~700 -200 720 -200 720 -201 713 -201 713 -203 707 -203 707 -201 700 -201 700 -200~#880000~1~0~none~gge5692~0",
          "LIB~625~-140~package`KEY-SMD_2P-L6.2-W3.6-LS8.0`Supplier Part`C118141`Supplier`LCSC`Manufacturer Part`K2-1107ST-A4SW-06`Contributor`LCEDA_Lib`制造商`韩国韩荣`spicePre`K`spiceSymbolName`K2-3.6×6.1_SMD`~~0~gge07d683b883fc0960~daacbe2eec304950b61eef2efe596556~5c1036b53a4146e4841df4ed0a9de8f0~0~7704f5a40f87cff2~yes~yes~~1586866326~#@$T~N~613.0703125~-153~0~#000080~Arial~~~~~comment~K2-3.6×6.1_SMD~1~start~gge5701~0~pinpart#@$T~P~613.0703125~-162~0~#000080~Arial~~~~~comment~KEY4~1~start~gge5707~0~pinpart#@$E~635~-140~2~2~#880000~1~0~none~gge5713~0#@$E~615~-140~2~2~#880000~1~0~none~gge5716~0#@$P~show~0~1~600~-140~180~gge5719~0^^600~-140^^M 600 -140 h 13~#880000^^0~615~-137~0~1~start~~~#0000FF^^1~611~-141~0~1~end~~~#0000FF^^0~610~-140^^0~M 613 -137 L 616 -140 L 613 -143#@$P~show~0~2~650~-140~0~gge5740~0^^650~-140^^M 650 -140 h -13~#880000^^0~635~-137~0~2~end~~~#0000FF^^1~640~-141~0~2~start~~~#0000FF^^0~640~-140^^0~M 637 -143 L 634 -140 L 637 -137#@$PL~615 -145 635 -145 635 -146 628 -146 628 -148 622 -148 622 -146 615 -146 615 -145~#880000~1~0~none~gge5761~0",
          "LIB~710~-140~package`KEY-SMD_2P-L6.2-W3.6-LS8.0`Supplier Part`C118141`Supplier`LCSC`Manufacturer Part`K2-1107ST-A4SW-06`Contributor`LCEDA_Lib`制造商`韩国韩荣`spicePre`K`spiceSymbolName`K2-3.6×6.1_SMD`~~0~gge2c0b088d449abb04~daacbe2eec304950b61eef2efe596556~5c1036b53a4146e4841df4ed0a9de8f0~0~cd6e53adf06aba88~yes~yes~~1586866326~#@$T~N~698.0703125~-153~0~#000080~Arial~~~~~comment~K2-3.6×6.1_SMD~1~start~gge5770~0~pinpart#@$T~P~698.0703125~-162~0~#000080~Arial~~~~~comment~KEY5~1~start~gge5776~0~pinpart#@$E~720~-140~2~2~#880000~1~0~none~gge5782~0#@$E~700~-140~2~2~#880000~1~0~none~gge5785~0#@$P~show~0~1~685~-140~180~gge5788~0^^685~-140^^M 685 -140 h 13~#880000^^0~700~-137~0~1~start~~~#0000FF^^1~696~-141~0~1~end~~~#0000FF^^0~695~-140^^0~M 698 -137 L 701 -140 L 698 -143#@$P~show~0~2~735~-140~0~gge5809~0^^735~-140^^M 735 -140 h -13~#880000^^0~720~-137~0~2~end~~~#0000FF^^1~725~-141~0~2~start~~~#0000FF^^0~725~-140^^0~M 722 -143 L 719 -140 L 722 -137#@$PL~700 -145 720 -145 720 -146 713 -146 713 -148 707 -148 707 -146 700 -146 700 -145~#880000~1~0~none~gge5830~0",
          "LIB~215~-420~package`C0805`nameAlias`Value`Supplier`LCSC`Manufacturer Part`C2012X7R1E224KT0H0N`Manufacturer`TDK`Supplier Part`C76640`JLCPCB Part Class`Extended Part`spicePre`C`spiceSymbolName`C2012X7R1E224KT0H0N`~~0~ggebcee51c0633ffb3f~2ee8eb13a0124a108e622ce40c0c25a8~a995ef493635e8ff05562ce08003c851~0~a09af3a9a71645f0~yes~yes~9abfb7fefe1a484ab1e8a8c564be3bf0~1701239839~d9efcf2716784caebba5d5226fd9b4ff#@$T~N~209.03125~-431~0~#000080~Arial~~~~~comment~220nF~1~start~gge6058~0~pinpart#@$T~P~209.03125~-440~0~#000080~Arial~~~~~comment~C1~1~start~gge6064~0~pinpart#@$PL~213 -428 213 -412~#880000~1~0~none~gge6070~0#@$PL~217 -428 217 -412~#880000~1~0~none~gge6073~0#@$P~show~1~1~200~-420~180~gge6076~0^^200~-420^^M 200 -420 h 10~#880000^^0~215~-417~0~1~start~~~#0000FF^^0~205~-421~0~1~end~~~#0000FF^^0~207~-420^^0~M 210 -417 L 213 -420 L 210 -423#@$P~show~1~2~230~-420~0~gge6097~0^^230~-420^^M 230 -420 h -10~#880000^^0~215~-417~0~2~end~~~#0000FF^^0~225~-421~0~2~start~~~#0000FF^^0~223~-420^^0~M 220 -423 L 217 -420 L 220 -417#@$PL~210 -420 213 -420~#880000~1~0~none~gge6118~0#@$PL~217 -420 220 -420~#880000~1~0~none~gge6121~0",
          "LIB~340~-405~package`R0603`nameAlias`Value`Supplier`LCSC`Manufacturer`UNI-ROYAL(厚声)`Manufacturer Part`0603WAF470JT5E`Supplier Part`C23182`JLCPCB Part Class`Basic Part`spicePre`R`spiceSymbolName`0603WAF470JT5E`~90~0~ggef7cd5d7c5f0f1ad8~398691f1f785460098bbe5ee6590333c~eb434b2d0361cebc504a90772dbca13c~0~473bb0276d779545~yes~yes~6e283842988f4a0b9b9b9b4a510e5e3a~1700616905~9274445e46564bdf9effaeb437ebf0f7#@$T~N~346~-392.64~0~#000080~Arial~~~~~comment~47Ω~1~start~gge6196~0~pinpart#@$T~P~354.03~-406.79~0~#000080~Arial~~~~~comment~R1~1~start~gge6202~0~pinpart#@$P~show~1~2~340~-425~90~gge6208~0^^340~-425^^M 340 -425 v 10~#880000^^0~343~-410~270~2~end~~~#0000FF^^0~339~-420~270~2~start~~~#0000FF^^0~340~-418^^0~M 337 -415 L 340 -412 L 343 -415#@$P~show~1~1~340~-385~270~gge6229~0^^340~-385^^M 340 -385 v -10~#880000^^0~343~-400~270~1~start~~~#0000FF^^0~339~-390~270~1~end~~~#0000FF^^0~340~-392^^0~M 343 -395 L 340 -398 L 337 -395#@$R~336~-415~~~8~20~#880000~1~0~none~gge6250~0~",
          "LIB~225~-495~package`QFN50P160X160X50-8N`Contributor`Gerriko io`spicePre`I`spiceSymbolName`NT3H2111W0FHKH`Manufacturer Part`NT3H2111W0FHKH`Supplier`LCSC`Manufacturer`NXP(恩智浦)`Supplier Part`C710403`~~0~gge8a1f93547ecb6f3f~9fbac4b5fc4846468424d1d9fa3e4752~bbafbdfa02364537bfd4df965c7b336a~0~9a8c334894958df3~yes~yes~~1614802867~#@$T~N~212.734375~-548~0~#000080~Arial~~~~~comment~NT3H2111W0FHKH~1~start~gge7666~0~pinpart#@$T~P~212.734375~-557~0~#000080~Arial~~~~~comment~IC1~1~start~gge7672~0~pinpart#@$R~165~-545~3~3~110~100~#880000~1~0~none~gge7678~0~#@$P~show~4~7~295~-505~0~gge7681~0^^295~-505^^M 295 -505 h -20~#880000^^1~272~-502~0~VOUT~end~~~#0000FF^^1~281~-506~0~7~start~~~#0000FF^^0~278~-505^^0~M 275 -508 L 272 -505 L 275 -502#@$P~show~0~2~145~-505~180~gge7702~0^^145~-505^^M 145 -505 h 20~#880000^^1~168~-502~0~VSS/GND~start~~~#0000FF^^1~159~-506~0~2~end~~~#0000FF^^0~162~-505^^0~M 165 -502 L 168 -505 L 165 -508#@$P~show~0~1~145~-525~180~gge7723~0^^145~-525^^M 145 -525 h 20~#880000^^1~168~-522~0~LA~start~~~#0000FF^^1~159~-526~0~1~end~~~#0000FF^^0~162~-525^^0~M 165 -522 L 168 -525 L 165 -528#@$P~show~0~8~295~-525~0~gge7744~0^^295~-525^^M 295 -525 h -20~#880000^^1~272~-522~0~LB~end~~~#0000FF^^1~281~-526~0~8~start~~~#0000FF^^0~278~-525^^0~M 275 -528 L 272 -525 L 275 -522#@$P~show~0~5~295~-465~0~gge7765~0^^295~-465^^M 295 -465 h -20~#880000^^1~272~-462~0~SDA~end~~~#0000FF^^1~281~-466~0~5~start~~~#0000FF^^0~278~-465^^0~M 275 -468 L 272 -465 L 275 -462#@$P~show~4~6~295~-485~0~gge7786~0^^295~-485^^M 295 -485 h -20~#880000^^1~272~-482~0~VCC~end~~~#0000FF^^1~281~-486~0~6~start~~~#0000FF^^0~278~-485^^0~M 275 -488 L 272 -485 L 275 -482#@$P~show~0~4~145~-465~180~gge7807~0^^145~-465^^M 145 -465 h 20~#880000^^1~168~-462~0~FD~start~~~#0000FF^^1~159~-466~0~4~end~~~#0000FF^^0~162~-465^^0~M 165 -462 L 168 -465 L 165 -468#@$P~show~0~3~145~-485~180~gge7828~0^^145~-485^^M 145 -485 h 20~#880000^^1~168~-482~0~SCL~start~~~#0000FF^^1~159~-486~0~3~end~~~#0000FF^^0~162~-485^^0~M 165 -482 L 168 -485 L 165 -488",
          "W~295 -525 340 -525 340 -550~#008800~1~0~none~gge9935~0",
          "W~340 -610 145 -610 145 -525~#008800~1~0~none~gge9938~0",
          "W~340 -425 340 -505 295 -505~#008800~1~0~none~gge9958~0",
          "W~130 -385 340 -385~#008800~1~0~none~gge9966~0",
          "W~145 -505 65 -505 65 -385 90 -385~#008800~1~0~none~gge9969~0",
          "W~200 -420 110 -420 110 -505~#008800~1~0~none~gge9972~0",
          "W~230 -420 305 -420 305 -505~#008800~1~0~none~gge9976~0",
          "W~975 -310 1075 -310 1075 -310 1085 -310 1100 -310 1100 -110 805 -110 805 -135 840 -135~#008800~1~0~none~gge9986~0",
          "W~955 -235 955 -225 960 -225 960 -135 895 -135 880 -135~#008800~1~0~none~gge9991~0",
          "W~825 -275 780 -275 780 -140 735 -140~#008800~1~0~none~gge12053~0",
          "W~600 -195 600 -140 515 -140 515 -285 825 -285~#008800~1~0~none~gge12059~0",
          "W~685 -195 650 -195~#008800~1~0~none~gge12076~0",
          "W~600 -195 585 -195~#008800~1~0~none~gge12079~0",
          "W~825 -235 815 -235 815 -180 1025 -180 1020 -180~#008800~1~0~none~gge12112~0",
          "W~825 -225 820 -225 820 -360 820 -360 685 -360 685 -360 685 -140 650 -140~#008800~1~0~none~gge12148~0",
          "LIB~1020~-385~package`OLED-TH_L27.8-W27.2-P2.54_C9900033791`Contributor`lcsc`Supplier`LCSC`Supplier Part`C5248080`Manufacturer`HS(汉昇)`Manufacturer Part`HS96L03W2C03`JLCPCB Part Class`Extended Part`spicePre`U`spiceSymbolName`HS96L03W2C03`~90~0~gge7273a6976e4ca946~17412ae1dd56412bab5905641ae023e4~4839e600161745f1af0afe53dafb495c~0~d624ba8bf3a93064~yes~yes~~1682302359~#@$T~N~1014.03~-403~0~#000080~Arial~~~~~comment~HS96L03W2C03~1~start~gge14787~0~pinpart#@$T~P~1014.03~-412.14~0~#000080~Arial~~~~~comment~U4~1~start~gge14793~0~pinpart#@$R~995~-400~2~2~50~30~#880000~1~0~none~gge14799~0~#@$E~1000~-375~1.5~1.5~#880000~1~0~#880000~gge14802~0#@$P~show~0~1~1005~-360~270~gge14805~0^^1005~-360^^M 1005 -360 v -10~#000000^^1~1009~-373.7~270~GND~start~~~#000000^^1~1004~-369.5~270~1~end~~~#000000^^0~1005~-367^^0~M 1008 -370 L 1005 -373 L 1002 -370#@$P~show~0~2~1015~-360~270~gge14826~0^^1015~-360^^M 1015 -360 v -10~#FF0000^^1~1019~-373.7~270~VCC~start~~~#FF0000^^1~1014~-369.5~270~2~end~~~#FF0000^^0~1015~-367^^0~M 1018 -370 L 1015 -373 L 1012 -370#@$P~show~0~3~1025~-360~270~gge14847~0^^1025~-360^^M 1025 -360 v -10~#880000^^1~1029~-373.7~270~SCL~start~~~#0000FF^^1~1024~-369.5~270~3~end~~~#0000FF^^0~1025~-367^^0~M 1028 -370 L 1025 -373 L 1022 -370#@$P~show~0~4~1035~-360~270~gge14868~0^^1035~-360^^M 1035 -360 v -10~#880000^^1~1039~-373.7~270~SDA~start~~~#0000FF^^1~1034~-369.5~270~4~end~~~#0000FF^^0~1035~-367^^0~M 1038 -370 L 1035 -373 L 1032 -370",
          "W~1025 -180 1025 -250 990 -250 990 -330 1005 -330 1005 -360~#008800~1~0~none~gge15001~0",
          "W~935 -235 945 -235 945 -230 980 -230 980 -100 685 -100 685 -140~#008800~1~0~none~gge15214~0",
          "W~935 -225 940 -225 940 -250 945 -250 945 -330 785 -330 785 -110 600 -110 600 -140~#008800~1~0~none~gge15217~0",
          "W~825 -255 805 -255 805 -310 600 -310 600 -195~#008800~1~0~none~gge15226~0",
          "R~440~-440~~~695~350~#000000~1~0~none~gge15241~0~",
          "R~30~-675~~~375~320~#000000~1~0~none~gge15244~0~",
          "T~L~785~-455~0~#0000FF~~9pt~~~~comment~computing~1~start~gge15247~0~pinpart",
          "T~L~190~-685~0~#0000FF~~9pt~~~~comment~nfc part~1~start~gge15253~0~pinpart",
          "W~1020 -110 1020 -180~#008800~1~0~none~gge15257~0",
          "R~500~-725~~~275~110~#000000~1~0~none~gge15263~0~",
          "T~L~615~-620~0~#0000FF~~9pt~~~~comment~9.5cm~1~start~gge15266~0~pinpart",
          "T~L~769.5~-654.11~270~#0000FF~~9pt~~~~comment~4.5 cm~1~~gge15272~0~pinpart",
          "T~L~615~-660~0~#0000FF~~9pt~undefined~undefined~~comment~CARD~1~start~gge15284~0~pinpart",
          "T~L~880~-670~0~#0000FF~~9pt~undefined~undefined~~comment~features:~1~start~gge15296~0~pinpart",
          "T~L~880~-645~0~#0000FF~~9pt~undefined~undefined~~comment~nfc transmission~1~start~gge15302~0~pinpart",
          "T~L~880~-630~0~#0000FF~~9pt~undefined~undefined~~comment~can run a game~1~start~gge15308~0~pinpart",
          "T~L~880~-615~0~#0000FF~~9pt~undefined~undefined~~comment~play video~1~start~gge15314~0~pinpart",
          "T~L~880~-600~0~#0000FF~~9pt~undefined~undefined~~comment~looks cool~1~start~gge15320~0~pinpart",
          "R~870~-695~~~120~110~#000000~1~0~none~gge15332~0~",
          "W~825 -265 735 -265 735 -140~#008800~1~0~none~gge15344~0",
          "W~935 -215 940 -215 940 -105 735 -105 735 -140~#008800~1~0~none~gge15348~0",
          "W~825 -215 535 -215 535 -195~#008800~1~0~none~gge15354~0",
          "LIB~860~-135~package`BAT-SMD_BS-1632-1`Contributor`LCSC`Supplier`LCSC`Supplier Part`C969910`Manufacturer`Q&J`Manufacturer Part`BS-1632-1`JLCPCB Part Class`Extended Part`spicePre`B`spiceSymbolName`BS-1632-1`~~0~gge8f63767ac9906fb2~c4e912aab88e44dbb95c44a58ddd595e~21dd0f3a12454d699dfafda322f56771~0~8617b6c6a3d6fad2~yes~yes~~1611214373~#@$T~N~851.44140625~-147~0~#000080~Arial~~~~~comment~BS-1632-1~1~start~gge15437~0~pinpart#@$T~P~851.44140625~-156~0~#000080~Arial~~~~~comment~BT1~1~start~gge15443~0~pinpart#@$P~show~1~2~880~-135~0~gge15449~0^^880~-135^^M 880 -135 h -15~#000000^^0~860~-132~0~2~end~~~#000000^^1~870~-136~0~2~start~~~#000000^^0~868~-135^^0~M 865 -138 L 862 -135 L 865 -132#@$P~show~1~1~840~-135~180~gge15470~0^^840~-135^^M 840 -135 h 15~#000000^^0~860~-132~0~1~start~~~#000000^^1~850~-136~0~1~end~~~#000000^^0~852~-135^^0~M 855 -132 L 858 -135 L 855 -138#@$PL~864 -140 864 -131~#880000~1~0~none~gge15491~0#@$PL~861 -144 861 -128~#880000~1~0~none~gge15494~0#@$PL~858 -140 858 -131~#880000~1~0~none~gge15497~0#@$PL~855 -144 855 -128~#880000~1~0~none~gge15500~0",
          "LIB~965~-245~package`SW-TH_3P-P4.80-HX-SS12D10G4`Supplier`LCSC`Supplier Part`C19189120`Manufacturer`hanxia(韩下)`Manufacturer Part`HX SS12D10G5`Contributor`lcsc`spicePre`U`spiceSymbolName`HX SS12D10G5`~270~0~gge9a6dc95d8d5deb42~78bbdfb5616c450394f6970db7f79341~5c9ae531fdf84d26be7fd53a91a9ffff~0~91409afc4ed53dd8~yes~yes~~1699347452~#@$T~N~961.02~-261.76~0~#000080~Arial~~~~~comment~HX SS12D10G5~1~start~gge16235~0~pinpart#@$T~P~961.53515625~-269~0~#000080~Arial~~~~~comment~U2~1~start~gge16241~0~pinpart#@$P~show~0~3~955~-235~180~gge16247~0^^955~-235^^M 955 -235 h 10~#880000^^0~967~-232~0~3~start~~~#0000FF^^1~965~-236~0~3~end~~~#0000FF^^0~962~-235^^0~M 965 -232 L 968 -235 L 965 -238#@$P~show~0~2~955~-245~180~gge16268~0^^955~-245^^M 955 -245 h 12~#880000^^0~969~-242~0~2~start~~~#0000FF^^1~965~-246~0~2~end~~~#0000FF^^0~964~-245^^0~M 967 -242 L 970 -245 L 967 -248#@$P~show~0~1~955~-255~180~gge16289~0^^955~-255^^M 955 -255 h 10~#880000^^0~967~-252~0~1~start~~~#0000FF^^1~965~-256~0~1~end~~~#0000FF^^0~962~-255^^0~M 965 -252 L 968 -255 L 965 -258#@$E~966~-255~1~1~#880000~1~0~none~gge16310~0#@$E~966~-245~1~1~#880000~1~0~none~gge16313~0#@$E~966~-235~1~1~#880000~1~0~none~gge16316~0#@$PL~969 -255 977 -255 977 -245 969 -245~#880000~1~0~none~gge16319~0#@$PL~969 -255 972 -256~#880000~1~0~none~gge16322~0#@$PL~969 -255 972 -254~#880000~1~0~none~gge16325~0#@$PL~969 -245 972 -244~#880000~1~0~none~gge16328~0#@$PL~969 -245 972 -246~#880000~1~0~none~gge16331~0#@$PL~969 -235 972 -236~#880000~1~0~none~gge16334~0#@$PL~969 -235 972 -234~#880000~1~0~none~gge16337~0#@$PL~970 -235 982 -235 982 -245 977 -245~#880000~1~0~none~gge16340~0",
          "W~955 -245 950 -245 950 -130 1020 -130~#008800~1~0~none~gge16476~0",
          "W~955 -255 955 -310 975 -310~#008800~1~0~none~gge16744~0",
          "W~1015 -360 1015 -330 1080 -330 1080 -310~#008800~1~0~none~gge16757~0",
          "W~825 -305 810 -305 810 -350 965 -350 965 -310~#008800~1~0~none~gge16762~0",
          "W~825 -245 805 -245 805 -190 1090 -190 1090 -310~#008800~1~0~none~gge16782~0",
          "LIB~342~-580~package`25X48MM_NFC_ANTENNA`Contributor`maggie.j.liu`spicePre`?`spiceSymbolName`25X48MM_NFC_ANTENNA`Manufacturer Part``~~0~gge629efb6203792360~f41eec537d614e94b29a6385c0a16281~74ed872066dc4a328ddd0a43e85acc5e~0~20a7f3bac4d890eb~yes~yes~aee2da9b3ee34ccfad21e011c5e94d3e~1676953278~6ff8044e052c44be82a2baf6ac8e6cd0#@$T~N~347~-568~0~#000080~Arial~~~~~comment~25X48MM_NFC_ANTENNA~1~start~gge16787~0~pinpart#@$T~P~347~-577~0~#000080~Arial~~~~~comment~2~1~start~gge16793~0~pinpart#@$A~M 340 -590.157 A 5 5 0 0 1 340 -580.157~~#A54B4B~1~0~none~gge16799~0#@$A~M 340 -580.157 A 5 5 0 0 1 340 -570.157~~#A54B4B~1~0~none~gge16802~0#@$A~M 340 -600.157 A 5 5 0 0 1 340 -590.157~~#A54B4B~1~0~none~gge16805~0#@$A~M 340 -570.157 A 5 5 0 0 1 340 -560.157~~#A54B4B~1~0~none~gge16808~0#@$P~show~3~P$1~340~-610~90~gge16811~0^^340~-610^^M 340 -610 v 9.842~#A54B4B^^0~342.953~-590.47~270~P$1~end~~4.5pt~#A54B4B^^0~338.03~-606.22~270~P$1~start~~4.5pt~#A54B4B^^0~340~-604^^0~M 337 -601 L 340 -598 L 343 -601#@$P~show~3~P$2~340~-550~270~gge16832~0^^340~-550^^M 340 -550 v -9.842~#A54B4B^^0~342.953~-569.84~270~P$2~start~~4.5pt~#A54B4B^^0~338.03~-554.094~270~P$2~end~~4.5pt~#A54B4B^^0~340~-556^^0~M 343 -559 L 340 -562 L 337 -559",
          "W~935 -285 1065 -285 1065 -350~#008800~1~0~none~gge16995~0",
          "W~1025 -350 1025 -360~#008800~1~0~none~gge16998~0",
          "W~935 -295 985 -295 985 -230 1085 -230 1085 -315 1090 -315~#008800~1~0~none~gge17096~0",
          "W~1090 -355 1090 -360 1035 -360~#008800~1~0~none~gge17099~0",
          "LIB~1090~-335~package`RES-TH_BD1.9-L3.4-P7.40-D0.5`Contributor`lcsc`Supplier`LCSC`Supplier Part`C1751043`Manufacturer`YAGEO(国巨)`Manufacturer Part`MF0204FRE52-1R54`JLCPCB Part Class`Extended Part`nameAlias`Value`spicePre`U`spiceSymbolName`MF0204FRE52-1R54`~90~0~ggee0a59b25130f7c8b~77928cef351446688851083c91bd25b6~0951502c8e28437c8828fa01f71b13f2~0~f679e801b147f19b~yes~yes~f2a121b7160244e99603e57b588fd779~1694493208~0e84608d83094674814800409327f87f#@$T~N~1097~-322.74~0~#000080~Arial~~~~~comment~1.54Ω~1~start~gge17102~0~pinpart#@$T~P~1097~-331.84~0~#000080~Arial~~~~~comment~U5~1~start~gge17108~0~pinpart#@$R~1085~-345~~~10~20~#A00000~1~0~none~gge17114~0~#@$P~show~0~2~1090~-355~90~gge17117~0^^1090~-355^^M 1090 -345 v -10~#800^^0~1090~-341~270~2~end~~~#800^^0~1086~-349~270~2~start~~~#800^^0~1090~-368^^0~M 1087 -365 L 1090 -362 L 1093 -365#@$P~show~0~1~1090~-315~270~gge17138~0^^1090~-315^^M 1090 -325 v 10~#800^^0~1090~-329~270~1~start~~~#800^^0~1086~-321~270~1~end~~~#800^^0~1090~-302^^0~M 1093 -305 L 1090 -308 L 1087 -305",
          "LIB~1045~-350~package`RES-TH_BD1.9-L3.4-P7.40-D0.5`Contributor`lcsc`Supplier`LCSC`Supplier Part`C1751043`Manufacturer`YAGEO(国巨)`Manufacturer Part`MF0204FRE52-1R54`JLCPCB Part Class`Extended Part`nameAlias`Value`spicePre`U`spiceSymbolName`MF0204FRE52-1R54`~180~0~gge00cfb19c58c850c3~77928cef351446688851083c91bd25b6~0951502c8e28437c8828fa01f71b13f2~0~2d396c7c63f8a7e3~yes~yes~f2a121b7160244e99603e57b588fd779~1694493208~0e84608d83094674814800409327f87f#@$T~N~1039.03~-358~0~#000080~Arial~~~~~comment~1.54Ω~1~start~gge17231~0~pinpart#@$T~P~1039.03~-367~0~#000080~Arial~~~~~comment~U6~1~start~gge17237~0~pinpart#@$R~1035~-355~~~20~10~#A00000~1~0~none~gge17243~0~#@$P~show~0~2~1025~-350~180~gge17246~0^^1025~-350^^M 1035 -350 h -10~#800^^0~1039~-350~0~2~start~~~#800^^0~1031~-354~0~2~end~~~#800^^0~1012~-350^^0~M 1015 -347 L 1018 -350 L 1015 -353#@$P~show~0~1~1065~-350~0~gge17267~0^^1065~-350^^M 1055 -350 h 10~#800^^0~1051~-350~0~1~end~~~#800^^0~1059~-354~0~1~start~~~#800^^0~1078~-350^^0~M 1075 -353 L 1072 -350 L 1075 -347",
          "LIB~110~-380~package`LED-SMD_L2.1-W1.0-RD_BLUE`Supplier`LCSC`Manufacturer`EVERLIGHT(亿光)`Manufacturer Part`12-215/BHC-ZLMRY/3C`Supplier Part`C61217`JLCPCB Part Class`Extended Part`spicePre`L`spiceSymbolName`12-215/BHC-ZLMRY/3C`~180~0~gge073ce5bef654b96f~b0340a8f8add4bb58c87fa78f2f7a498~36e091cd019145b7affa54ad7cf42056~0~0e28cadef7c1e35e~yes~yes~fdb7985c7dba4f40919ccc5d9760b0c9~1698199521~de29824718b74122bbf5951bb1282ee7#@$T~N~98.33~-396~0~#000080~Arial~~~~~comment~12-215/BHC-ZLMRY/3C~1~start~gge17903~0~pinpart#@$T~P~98.33~-405.05~0~#000080~Arial~~~~~comment~LED1~1~start~gge17909~0~pinpart#@$PT~M 125 -372 L 121 -374 L 123 -376 Z ~#880000~1~0~#880000~gge17915~0~#@$PT~M 121 -368 L 117 -370 L 119 -372 Z ~#880000~1~0~#880000~gge17918~0~#@$P~show~0~1~130~-385~0~gge17921~0^^130~-385^^M 130 -385 h -15~#800^^0~111~-385~0~K~end~~~#800^^0~119~-389~0~1~start~~~#800^^0~118~-385^^0~M 115 -388 L 112 -385 L 115 -382#@$PL~118 -379 125 -372~#880000~1~0~none~gge17942~0#@$PL~114 -375 121 -368~#880000~1~0~none~gge17945~0#@$P~show~0~2~90~-385~180~gge17948~0^^90~-385^^M 90 -385 h 15~#800^^0~109~-385~0~A~start~~~#800^^0~101~-389~0~2~end~~~#800^^0~102~-385^^0~M 105 -382 L 108 -385 L 105 -388#@$PL~115 -377 115 -393~#880000~1~0~none~gge17969~0#@$PT~M 105 -391 L 115 -385 L 105 -378 Z ~#880000~1~0~#880000~gge17972~0~",
          "J~110~-505~2.5~#CC0000~gge9973~0",
          "J~305~-505~2.5~#CC0000~gge9977~0",
          "J~735~-140~2.5~#CC0000~gge12121~0",
          "J~600~-140~2.5~#CC0000~gge12130~0",
          "J~600~-195~2.5~#CC0000~gge12135~0",
          "J~1020~-110~2.5~#CC0000~gge15258~0",
          "J~735~-195~2.5~#CC0000~gge15345~0",
          "J~685~-140~2.5~#CC0000~gge12119~0",
          "J~685~-195~2.5~#CC0000~gge12120~0",
          "J~1020~-130~2.5~#CC0000~gge16477~0",
          "J~1080~-310~2.5~#CC0000~gge16758~0",
          "J~965~-310~2.5~#CC0000~gge16763~0",
          "J~1090~-310~2.5~#CC0000~gge16783~0",
          "J~1025~-180~2.5~#CC0000~gge17798~0"
        ],
        "BBox": {
          "x": 0,
          "y": -790.6,
          "width": 1149,
          "height": 807.1
        },
        "colors": {
          "select": "#FF0000"
        }
      }
    },
    {
      "docType": "1",
      "title": "schem1 copy",
      "description": "",
      "dataStr": {
        "head": {
          "docType": "1",
          "editorVersion": "6.5.47",
          "newgId": true,
          "c_para": {
            "Prefix Start": "1"
          },
          "c_spiceCmd": "null",
          "hasIdFlag": true,
          "uuid": "9f8223938e694a50bf0b00c91d4dff86",
          "x": "0",
          "y": "0",
          "portOfADImportHack": "",
          "importFlag": 0,
          "transformList": ""
        },
        "canvas": "CA~1000~1000~#FFFFFF~yes~#CCCCCC~15~1000~1000~line~5~pixel~5~0~0",
        "shape": [
          "LIB~0~-790~package`NONE`Manufacturer Part`?`spicePre`.`~~0~frame_lib_1~~~0~~yes~yes~~~#@$T~N~570.5~-793~0~#880000~Arial~~~~~comment~A~0~start~gge223~0~#@$PT~M 206 -780 L 206 -790 M 206 6 L 206 16 M 402 -780 L 402 -790 M 402 6 L 402 16 M 598 -780 L 598 -790 M 598 6 L 598 16 M 794 -780 L 794 -790 M 794 6 L 794 16 M 990 -780 L 990 -790 M 990 6 L 990 16 M 10 -584 L 0 -584 M 1139 -584 L 1149 -584 M 10 -388 L 0 -388 M 1139 -388 L 1149 -388 M 10 -192 L 0 -192 M 1139 -192 L 1149 -192 M 10 4 L 0 4 M 1139 4 L 1149 4~#880000~1~0~none~gge10~0~frame_tick#@$T~P~571.5~-802~0~#880000~Arial~~~~~comment~A~0~start~gge220~0~#@$T~L~1.5~-682~0~#880000~~~~~~comment~A~1~start~gge13~0~frame_tick#@$T~L~1140.5~-682~0~#880000~~~~~~comment~A~1~start~gge19~0~frame_tick#@$T~L~1.5~-486~0~#880000~~~~~~comment~B~1~start~gge25~0~frame_tick#@$T~L~1140.5~-486~0~#880000~~~~~~comment~B~1~start~gge31~0~frame_tick#@$T~L~1.5~-290~0~#880000~~~~~~comment~C~1~start~gge37~0~frame_tick#@$T~L~1140.5~-290~0~#880000~~~~~~comment~C~1~start~gge43~0~frame_tick#@$T~L~1.5~-94~0~#880000~~~~~~comment~D~1~start~gge49~0~frame_tick#@$T~L~1140.5~-94~0~#880000~~~~~~comment~D~1~start~gge55~0~frame_tick#@$T~L~108~-781.5~0~#880000~~~~~~comment~1~1~start~gge61~0~frame_tick#@$T~L~108~14.5~0~#880000~~~~~~comment~1~1~start~gge67~0~frame_tick#@$T~L~304~-781.5~0~#880000~~~~~~comment~2~1~start~gge73~0~frame_tick#@$T~L~304~14.5~0~#880000~~~~~~comment~2~1~start~gge79~0~frame_tick#@$T~L~500~-781.5~0~#880000~~~~~~comment~3~1~start~gge85~0~frame_tick#@$T~L~500~14.5~0~#880000~~~~~~comment~3~1~start~gge91~0~frame_tick#@$T~L~696~-781.5~0~#880000~~~~~~comment~4~1~start~gge97~0~frame_tick#@$T~L~696~14.5~0~#880000~~~~~~comment~4~1~start~gge103~0~frame_tick#@$T~L~892~-781.5~0~#880000~~~~~~comment~5~1~start~gge109~0~frame_tick#@$T~L~892~14.5~0~#880000~~~~~~comment~5~1~start~gge115~0~frame_tick#@$R~10~-780~~~1129~786~#880000~1~0~none~gge121~0~frame_innerbox#@$R~0~-790~~~1149~806~#880000~1~0~none~gge124~0~frame_outbox#@$R~694.99995~-74~~~444~80~#880000~1~0~none~gge127~0~frame_hitarea#@$PL~695.1 -34.75 1138.63 -34.75~#880000~1~0~none~gge130~0#@$PL~799.63 -14.75 1138.63 -14.75~#880000~1~0~none~gge133~0#@$PL~1059.61 -73.93 1059.63 -34.75~#880000~1~0~none~gge136~0#@$PL~1059.63 -34.75 1059.63 -14.75~#880000~1~0~none~gge139~0#@$T~L~699.99995~-61~0~#880000~~8pt~~~~comment~TITLE:~1~start~gge142~0~pinpart#@$T~L~757.62495~-48.41~0~#880000~~10pt~~~~comment~pcb_busniness card~1~start~gge148~0~frame_title#@$T~L~1064.62495~-47.75~0~#880000~~8pt~~~~comment~REV:~1~start~gge154~0~pinpart#@$T~L~1102.62495~-47.75~0~#880000~~9pt~~~~comment~1.0~1~start~gge160~0~frame_version#@$T~L~804.62495~1~0~#880000~~8pt~~~~comment~Date:~1~start~gge166~0~pinpart#@$T~L~851.62495~1.48~0~#880000~~9pt~~~~comment~2024-07-21~1~start~gge172~0~frame_date#@$T~L~1063.62495~-19~0~#880000~~8pt~~~~comment~Sheet:~1~start~gge178~0~pinpart#@$T~L~1108.62495~-18.52~0~#880000~~9pt~~~~comment~1/1~1~start~gge184~0~frame_sheet#@$T~L~943.62495~1.25~0~#880000~~8pt~~~~comment~Drawn By:~1~start~gge190~0~pinpart#@$T~L~1008.63~1.25~0~#880000~~9pt~~~~comment~ministermonkeya1~1~start~gge196~0~frame_drawn#@$T~L~804.62495~-20.75~0~#880000~~8pt~~~~comment~Company:~1~start~gge202~0~pinpart#@$T~L~871.24995~-20.64~0~#880000~~9pt~~~~comment~Your Company~1~start~gge208~0~frame_company#@$PL~799.63 -34.75 799.63 5.25~#880000~1~0~none~gge214~0",
          "LIB~215~-420~package`C0805`nameAlias`Value`Supplier`LCSC`Manufacturer Part`C2012X7R1E224KT0H0N`Manufacturer`TDK`Supplier Part`C76640`JLCPCB Part Class`Extended Part`spicePre`C`spiceSymbolName`C2012X7R1E224KT0H0N`~~0~ggee46b1aecb3ea7690~2ee8eb13a0124a108e622ce40c0c25a8~a995ef493635e8ff05562ce08003c851~0~~yes~yes~9abfb7fefe1a484ab1e8a8c564be3bf0~1701239839~d9efcf2716784caebba5d5226fd9b4ff#@$T~N~209.03125~-431~0~#000080~Arial~~~~~comment~220nF~1~start~gge6058~0~#@$T~P~209.03125~-440~0~#000080~Arial~~~~~comment~C2~1~start~gge6064~0~#@$PL~213 -428 213 -412~#880000~1~0~none~gge6070~0#@$PL~217 -428 217 -412~#880000~1~0~none~gge6073~0#@$P~show~1~1~200~-420~180~gge6076~0^^200~-420^^M 200 -420 h 10~#880000^^0~215~-417~0~1~start~~~#0000FF^^0~205~-421~0~1~end~~~#0000FF^^0~207~-420^^0~M 210 -417 L 213 -420 L 210 -423#@$P~show~1~2~230~-420~0~gge6097~0^^230~-420^^M 230 -420 h -10~#880000^^0~215~-417~0~2~end~~~#0000FF^^0~225~-421~0~2~start~~~#0000FF^^0~223~-420^^0~M 220 -423 L 217 -420 L 220 -417#@$PL~210 -420 213 -420~#880000~1~0~none~gge6118~0#@$PL~217 -420 220 -420~#880000~1~0~none~gge6121~0",
          "LIB~340~-405~package`R0603`nameAlias`Value`Supplier`LCSC`Manufacturer`UNI-ROYAL(厚声)`Manufacturer Part`0603WAF470JT5E`Supplier Part`C23182`JLCPCB Part Class`Basic Part`spicePre`R`spiceSymbolName`0603WAF470JT5E`~90~0~gge0106f8a4a9432985~398691f1f785460098bbe5ee6590333c~eb434b2d0361cebc504a90772dbca13c~0~~yes~yes~6e283842988f4a0b9b9b9b4a510e5e3a~1700616905~9274445e46564bdf9effaeb437ebf0f7#@$T~N~346~-392.64~0~#000080~Arial~~~~~comment~47Ω~1~start~gge6196~0~#@$T~P~354.03~-406.79~0~#000080~Arial~~~~~comment~R2~1~start~gge6202~0~#@$P~show~1~2~340~-425~90~gge6208~0^^340~-425^^M 340 -425 v 10~#880000^^0~343~-410~270~2~end~~~#0000FF^^0~339~-420~270~2~start~~~#0000FF^^0~340~-418^^0~M 337 -415 L 340 -412 L 343 -415#@$P~show~1~1~340~-385~270~gge6229~0^^340~-385^^M 340 -385 v -10~#880000^^0~343~-400~270~1~start~~~#0000FF^^0~339~-390~270~1~end~~~#0000FF^^0~340~-392^^0~M 343 -395 L 340 -398 L 337 -395#@$R~336~-415~~~8~20~#880000~1~0~none~gge6250~0~",
          "LIB~225~-495~package`QFN50P160X160X50-8N`Contributor`Gerriko io`spicePre`I`spiceSymbolName`NT3H2111W0FHKH`Manufacturer Part`NT3H2111W0FHKH`Supplier`LCSC`Manufacturer`NXP(恩智浦)`Supplier Part`C710403`~~0~gge501380ea8d8f22b0~9fbac4b5fc4846468424d1d9fa3e4752~bbafbdfa02364537bfd4df965c7b336a~0~~yes~yes~~1614802867~#@$T~N~212.734375~-548~0~#000080~Arial~~~~~comment~NT3H2111W0FHKH~1~start~gge7666~0~#@$T~P~212.734375~-557~0~#000080~Arial~~~~~comment~IC2~1~start~gge7672~0~#@$R~165~-545~3~3~110~100~#880000~1~0~none~gge7678~0~#@$P~show~4~7~295~-505~0~gge7681~0^^295~-505^^M 295 -505 h -20~#880000^^1~272~-502~0~VOUT~end~~~#0000FF^^1~281~-506~0~7~start~~~#0000FF^^0~278~-505^^0~M 275 -508 L 272 -505 L 275 -502#@$P~show~0~2~145~-505~180~gge7702~0^^145~-505^^M 145 -505 h 20~#880000^^1~168~-502~0~VSS/GND~start~~~#0000FF^^1~159~-506~0~2~end~~~#0000FF^^0~162~-505^^0~M 165 -502 L 168 -505 L 165 -508#@$P~show~0~1~145~-525~180~gge7723~0^^145~-525^^M 145 -525 h 20~#880000^^1~168~-522~0~LA~start~~~#0000FF^^1~159~-526~0~1~end~~~#0000FF^^0~162~-525^^0~M 165 -522 L 168 -525 L 165 -528#@$P~show~0~8~295~-525~0~gge7744~0^^295~-525^^M 295 -525 h -20~#880000^^1~272~-522~0~LB~end~~~#0000FF^^1~281~-526~0~8~start~~~#0000FF^^0~278~-525^^0~M 275 -528 L 272 -525 L 275 -522#@$P~show~0~5~295~-465~0~gge7765~0^^295~-465^^M 295 -465 h -20~#880000^^1~272~-462~0~SDA~end~~~#0000FF^^1~281~-466~0~5~start~~~#0000FF^^0~278~-465^^0~M 275 -468 L 272 -465 L 275 -462#@$P~show~4~6~295~-485~0~gge7786~0^^295~-485^^M 295 -485 h -20~#880000^^1~272~-482~0~VCC~end~~~#0000FF^^1~281~-486~0~6~start~~~#0000FF^^0~278~-485^^0~M 275 -488 L 272 -485 L 275 -482#@$P~show~0~4~145~-465~180~gge7807~0^^145~-465^^M 145 -465 h 20~#880000^^1~168~-462~0~FD~start~~~#0000FF^^1~159~-466~0~4~end~~~#0000FF^^0~162~-465^^0~M 165 -462 L 168 -465 L 165 -468#@$P~show~0~3~145~-485~180~gge7828~0^^145~-485^^M 145 -485 h 20~#880000^^1~168~-482~0~SCL~start~~~#0000FF^^1~159~-486~0~3~end~~~#0000FF^^0~162~-485^^0~M 165 -482 L 168 -485 L 165 -488",
          "W~295 -525 325 -525 325 -550~#008800~1~0~none~gge9935~0",
          "W~325 -610 145 -610 145 -525~#008800~1~0~none~gge9938~0",
          "W~340 -425 340 -505 295 -505~#008800~1~0~none~gge9958~0",
          "W~130 -385 340 -385~#008800~1~0~none~gge9966~0",
          "W~145 -505 65 -505 65 -385 90 -385~#008800~1~0~none~gge9969~0",
          "W~200 -420 110 -420 110 -505~#008800~1~0~none~gge9972~0",
          "W~230 -420 305 -420 305 -505~#008800~1~0~none~gge9976~0",
          "R~30~-675~~~375~320~#000000~1~0~none~gge15244~0~",
          "T~L~190~-685~0~#0000FF~~9pt~~~~comment~nfc part~1~start~gge15253~0~pinpart",
          "R~500~-725~~~275~110~#000000~1~0~none~gge15263~0~",
          "T~L~615~-620~0~#0000FF~~9pt~~~~comment~9.5cm~1~start~gge15266~0~pinpart",
          "T~L~769.5~-654.11~270~#0000FF~~9pt~~~~comment~4.5 cm~1~~gge15272~0~pinpart",
          "T~L~615~-660~0~#0000FF~~9pt~undefined~undefined~~comment~CARD~1~start~gge15284~0~pinpart",
          "T~L~880~-670~0~#0000FF~~9pt~undefined~undefined~~comment~features:~1~start~gge15296~0~pinpart",
          "T~L~880~-645~0~#0000FF~~9pt~undefined~undefined~~comment~nfc transmission~1~start~gge15302~0~pinpart",
          "T~L~880~-630~0~#0000FF~~9pt~undefined~undefined~~comment~can run a game~1~start~gge15308~0~pinpart",
          "T~L~880~-615~0~#0000FF~~9pt~undefined~undefined~~comment~play video~1~start~gge15314~0~pinpart",
          "T~L~880~-600~0~#0000FF~~9pt~undefined~undefined~~comment~looks cool~1~start~gge15320~0~pinpart",
          "R~870~-695~~~120~110~#000000~1~0~none~gge15332~0~",
          "LIB~110~-380~package`LED-SMD_L2.1-W1.0-RD_BLUE`Supplier`LCSC`Manufacturer`EVERLIGHT(亿光)`Manufacturer Part`12-215/BHC-ZLMRY/3C`Supplier Part`C61217`JLCPCB Part Class`Extended Part`spicePre`L`spiceSymbolName`12-215/BHC-ZLMRY/3C`~180~0~gge886e8129123aa3a8~b0340a8f8add4bb58c87fa78f2f7a498~36e091cd019145b7affa54ad7cf42056~0~~yes~yes~fdb7985c7dba4f40919ccc5d9760b0c9~1698199521~de29824718b74122bbf5951bb1282ee7#@$T~N~98.33~-396~0~#000080~Arial~~~~~comment~12-215/BHC-ZLMRY/3C~1~start~gge17903~0~#@$T~P~98.33~-405.05~0~#000080~Arial~~~~~comment~LED2~1~start~gge17909~0~#@$PT~M 125 -372 L 121 -374 L 123 -376 Z ~#880000~1~0~#880000~gge17915~0~#@$PT~M 121 -368 L 117 -370 L 119 -372 Z ~#880000~1~0~#880000~gge17918~0~#@$P~show~0~1~130~-385~0~gge17921~0^^130~-385^^M 130 -385 h -15~#800^^0~111~-385~0~K~end~~~#800^^0~119~-389~0~1~start~~~#800^^0~118~-385^^0~M 115 -388 L 112 -385 L 115 -382#@$PL~118 -379 125 -372~#880000~1~0~none~gge17942~0#@$PL~114 -375 121 -368~#880000~1~0~none~gge17945~0#@$P~show~0~2~90~-385~180~gge17948~0^^90~-385^^M 90 -385 h 15~#800^^0~109~-385~0~A~start~~~#800^^0~101~-389~0~2~end~~~#800^^0~102~-385^^0~M 105 -382 L 108 -385 L 105 -388#@$PL~115 -377 115 -393~#880000~1~0~none~gge17969~0#@$PT~M 105 -391 L 115 -385 L 105 -378 Z ~#880000~1~0~#880000~gge17972~0~",
          "LIB~327~-580~package`25X48MM_NFC_ANTENNA`Contributor`dnonoo`spicePre`?`spiceSymbolName`25X48MM_NFC_ANTENNA`Manufacturer Part``~~0~ggea9e1bc3585c87492~565bdc94a5494250b01f75db9b3cfb94~67de74237f294d1498cefd45571b7bfc~0~~yes~yes~~1571586907~#@$T~N~332~-567.95~0~#000080~Arial~~~~~comment~25X48MM_NFC_ANTENNA~1~start~gge17976~0~#@$T~P~332~-576.97~0~#000080~Arial~~~~~comment~1~1~start~gge17982~0~#@$A~M 325 -590.157 A 5 5 0 0 1 325 -580.157~~#A54B4B~1~0~none~gge17988~0#@$A~M 325 -580.157 A 5 5 0 0 1 325 -570.157~~#A54B4B~1~0~none~gge17991~0#@$A~M 325 -600.157 A 5 5 0 0 1 325 -590.157~~#A54B4B~1~0~none~gge17994~0#@$A~M 325 -570.157 A 5 5 0 0 1 325 -560.157~~#A54B4B~1~0~none~gge17997~0#@$P~show~3~P$1~325~-610~90~gge18000~0^^325~-610^^M 325 -610 v 9.842~#A54B4B^^0~327.953~-590.47~270~P$1~end~~4.5pt~#A54B4B^^0~323.03~-606.22~270~P$1~start~~4.5pt~#A54B4B^^0~325~-604^^0~M 322 -601 L 325 -598 L 328 -601#@$P~show~3~P$2~325~-550~270~gge18021~0^^325~-550^^M 325 -550 v -9.842~#A54B4B^^0~327.953~-569.84~270~P$2~start~~4.5pt~#A54B4B^^0~323.03~-554.094~270~P$2~end~~4.5pt~#A54B4B^^0~325~-556^^0~M 328 -559 L 325 -562 L 322 -559",
          "J~110~-505~2.5~#CC0000~gge9973~0",
          "J~305~-505~2.5~#CC0000~gge9977~0"
        ],
        "BBox": {
          "x": 0,
          "y": -791,
          "width": 1149,
          "height": 807.1
        },
        "colors": {
          "select": "#FF0000"
        }
      }
    }
  ]
}